[
	{
		"title": "",
		"done": false
	},
	{
		"title": "",
		"done": false
	},
	{
		"title": "",
		"done": false
	},
	{
		"title": "",
		"done": false
	},
	{
		"title": "",
		"done": false
	},
	{
		"title": "",
		"done": false
	},
	{
		"title": "",
		"done": false
	},
	{
		"title": "",
		"done": false
	},
	{
		"title": "hi yoni",
		"done": false
	},
	{
		"title": "hi mule ",
		"done": false
	},
	{
		"title": "hi john ",
		"done": true
	},
	{
		"title": "",
		"done": false
	},
	{
		"title": "",
		"done": false
	},
	{
		"title": "",
		"done": false
	}
]